[{"test_idx": 0, "topology_provider": "snd_lib", "topology_name": "abilene", "#nodes": 12, "#links": 30, "provider": "mcf", "#demands": 182, "active_pairs_fraction": 0.2, "flows_per_pair": 7, "mcf_method": "maximal", "seed": 318924135, "sample_idx": 0, "ilp_method": "", "algorithm": "inverse_capacity", "objective": 2.2500000000000004, "execution_time": 0.0036829999999996588, "process_time": 0.0036730000000000373, "#waypoints": 182, "#weights": 30, "#loads": 30},
{"test_idx": 1, "topology_provider": "snd_lib", "topology_name": "abilene", "#nodes": 12, "#links": 30, "provider": "mcf", "#demands": 182, "active_pairs_fraction": 0.2, "flows_per_pair": 7, "mcf_method": "maximal", "seed": 318924135, "sample_idx": 1, "ilp_method": "", "algorithm": "inverse_capacity", "objective": 2.0000000000000004, "execution_time": 0.003978000000000037, "process_time": 0.003970999999999947, "#waypoints": 182, "#weights": 30, "#loads": 30},
{"test_idx": 2, "topology_provider": "snd_lib", "topology_name": "abilene", "#nodes": 12, "#links": 30, "provider": "mcf", "#demands": 182, "active_pairs_fraction": 0.2, "flows_per_pair": 7, "mcf_method": "maximal", "seed": 318924135, "sample_idx": 2, "ilp_method": "", "algorithm": "inverse_capacity", "objective": 2.0000000000000004, "execution_time": 0.003786999999999985, "process_time": 0.0037810000000000343, "#waypoints": 182, "#weights": 30, "#loads": 30},
{"test_idx": 3, "topology_provider": "snd_lib", "topology_name": "abilene", "#nodes": 12, "#links": 30, "provider": "mcf", "#demands": 182, "active_pairs_fraction": 0.2, "flows_per_pair": 7, "mcf_method": "maximal", "seed": 318924135, "sample_idx": 3, "ilp_method": "", "algorithm": "inverse_capacity", "objective": 1.2499999999999996, "execution_time": 0.005336999999999925, "process_time": 0.005321000000000353, "#waypoints": 182, "#weights": 30, "#loads": 30},
{"test_idx": 4, "topology_provider": "snd_lib", "topology_name": "abilene", "#nodes": 12, "#links": 30, "provider": "mcf", "#demands": 182, "active_pairs_fraction": 0.2, "flows_per_pair": 7, "mcf_method": "maximal", "seed": 318924135, "sample_idx": 4, "ilp_method": "", "algorithm": "inverse_capacity", "objective": 1.5000000000000002, "execution_time": 0.004754000000000147, "process_time": 0.004745000000000665, "#waypoints": 182, "#weights": 30, "#loads": 30},
{"test_idx": 5, "topology_provider": "snd_lib", "topology_name": "abilene", "#nodes": 12, "#links": 30, "provider": "mcf", "#demands": 182, "active_pairs_fraction": 0.2, "flows_per_pair": 7, "mcf_method": "maximal", "seed": 318924135, "sample_idx": 5, "ilp_method": "", "algorithm": "inverse_capacity", "objective": 1.2499999999999996, "execution_time": 0.0038549999999997198, "process_time": 0.0038489999999997693, "#waypoints": 182, "#weights": 30, "#loads": 30},
{"test_idx": 6, "topology_provider": "snd_lib", "topology_name": "abilene", "#nodes": 12, "#links": 30, "provider": "mcf", "#demands": 182, "active_pairs_fraction": 0.2, "flows_per_pair": 7, "mcf_method": "maximal", "seed": 318924135, "sample_idx": 6, "ilp_method": "", "algorithm": "inverse_capacity", "objective": 2.0, "execution_time": 0.0039000000000006807, "process_time": 0.0038960000000001216, "#waypoints": 182, "#weights": 30, "#loads": 30},
{"test_idx": 7, "topology_provider": "snd_lib", "topology_name": "abilene", "#nodes": 12, "#links": 30, "provider": "mcf", "#demands": 182, "active_pairs_fraction": 0.2, "flows_per_pair": 7, "mcf_method": "maximal", "seed": 318924135, "sample_idx": 7, "ilp_method": "", "algorithm": "inverse_capacity", "objective": 2.0, "execution_time": 0.0037479999999998626, "process_time": 0.0037409999999997723, "#waypoints": 182, "#weights": 30, "#loads": 30},
{"test_idx": 8, "topology_provider": "snd_lib", "topology_name": "abilene", "#nodes": 12, "#links": 30, "provider": "mcf", "#demands": 182, "active_pairs_fraction": 0.2, "flows_per_pair": 7, "mcf_method": "maximal", "seed": 318924135, "sample_idx": 8, "ilp_method": "", "algorithm": "inverse_capacity", "objective": 2.0000000000000004, "execution_time": 0.003807000000000116, "process_time": 0.0038010000000001654, "#waypoints": 182, "#weights": 30, "#loads": 30},
{"test_idx": 9, "topology_provider": "snd_lib", "topology_name": "abilene", "#nodes": 12, "#links": 30, "provider": "mcf", "#demands": 182, "active_pairs_fraction": 0.2, "flows_per_pair": 7, "mcf_method": "maximal", "seed": 318924135, "sample_idx": 9, "ilp_method": "", "algorithm": "inverse_capacity", "objective": 2.2500000000000004, "execution_time": 0.0033949999999993707, "process_time": 0.00338999999999956, "#waypoints": 182, "#weights": 30, "#loads": 30}]